modulitiz/browser/AbstractModuloBrowser.py
modulitiz/browser/ModuloBrowser.py
modulitiz/browser/TextToBePresentInElements.py
modulitiz/browser/constants/BrowserConstants.py
modulitiz/browser/constants/JsScripts.py
modulitiz/browser/enums/BrowserAddonExtensionEnum.py
modulitiz/browser/enums/BrowserImagePermissionsEnum.py
modulitiz/browser/enums/BrowserPageStatusEnum.py
modulitiz/browser/enums/BrowserProxyTypeEnum.py
modulitiz/charts/ModuloCharts.py
modulitiz/gui/AbstractGuiBean.py
modulitiz/gui/modulo_gui.py
modulitiz/gui/componenti/Bottone.py
modulitiz/gui/componenti/VerticalScrolledFrame.py
modulitiz/multimedia/ModuloImmagini.py
modulitiz/multimedia/audio/mp3/ModuloMp3.py
modulitiz/multimedia/audio/mp3/ModuloMp3Tags.py
modulitiz/multimedia/audio/mp3/beans/Mp3InfoBean.py
modulitiz/multimedia/audio/musicvisualizer/AudioAnalyzer.py
modulitiz/multimedia/audio/musicvisualizer/ModuloMusicVisualizer.py
modulitiz-2.23.0.dist-info/licenses/LICENSE
modulitiz-2.23.0.dist-info/METADATA
modulitiz-2.23.0.dist-info/WHEEL
modulitiz-2.23.0.dist-info/top_level.txt
modulitiz-2.23.0.dist-info/RECORD
