Metadata-Version: 2.4
Name: modulitiz
Version: 2.23.0
Summary: Raccolta dei miei moduli - versione completa
Author-email: tiz <sderfo1234@altervista.org>
Classifier: Programming Language :: Python :: 3
Classifier: Operating System :: OS Independent
Requires-Python: >=3.11
License-File: LICENSE
Requires-Dist: modulitiz-mini>=2
Requires-Dist: dash==3.4.0
Requires-Dist: librosa==0.11.0
Requires-Dist: matplotlib==3.10.8
Requires-Dist: mutagen==1.47.0
Requires-Dist: numpy==2.3.5
Requires-Dist: Pillow==12.1.0
Requires-Dist: pygame==2.6.1
Requires-Dist: selenium==4.40.0
Dynamic: license-file
